LICENSE
README.md
pyproject.toml
setup.py
SleepHarmonizer/PSGEventManager.py
SleepHarmonizer/Plugin.py
SleepHarmonizer/SignalPreprocessing.py
SleepHarmonizer/__init__.py
SleepHarmonizer/config.yaml
SleepHarmonizer.egg-info/PKG-INFO
SleepHarmonizer.egg-info/SOURCES.txt
SleepHarmonizer.egg-info/dependency_links.txt
SleepHarmonizer.egg-info/requires.txt
SleepHarmonizer.egg-info/top_level.txt
SleepHarmonizer/phases/Export.py
SleepHarmonizer/phases/LoadData.py
SleepHarmonizer/phases/__init__.py
SleepHarmonizer/recordloaders/AliceRMLLoader.py
SleepHarmonizer/recordloaders/AliceTextReportLoader.py
SleepHarmonizer/recordloaders/RecordLoaderAlice.py
SleepHarmonizer/recordloaders/RecordLoaderTest.py
SleepHarmonizer/recordloaders/__init__.py
SleepHarmonizer/recordwriter/RecordWriter.py
SleepHarmonizer/recordwriter/RecordWriterDICOM.py
SleepHarmonizer/recordwriter/RecordWriterEDF.py
SleepHarmonizer/recordwriter/__init__.py
tests/__init__.py
tests/conftest.py
tests/unit/__init__.py
tests/unit/test_Export.py
tests/unit/test_LoadData.py
tests/unit/test_Plugin.py
tests/unit/test_SignalPreprocessing.py