Metadata-Version: 2.4
Name: SleepHarmonizer
Version: 0.6.5
Summary: A Plugin and stand alone tool to harmonize sleep related data
Home-page: https://gitlab.com/sleep-is-all-you-need/sleep-harmonizer
Author: Franz Ehrlich
Author-email: fehrlichd@gmail.com
Classifier: Programming Language :: Python :: 3
Classifier: License :: OSI Approved :: MIT License
Classifier: Operating System :: OS Independent
Requires-Python: >=3.5
License-File: LICENSE
Requires-Dist: pyPhases
Requires-Dist: pyPhasesRecordloader
Requires-Dist: pyPhasesRecordloaderPhysionet
Requires-Dist: pyPhasesRecordloaderSHHS
Requires-Dist: pyPhasesRecordLoaderMrOS
Requires-Dist: pyPhasesRecordloaderMESA
Requires-Dist: pyPhasesRecordloaderProfusion
Requires-Dist: pyPhasesRecordloaderNox
Requires-Dist: phases
Requires-Dist: numpy
Requires-Dist: tqdm
Requires-Dist: pydicom
Requires-Dist: pyedflib
Dynamic: author
Dynamic: author-email
Dynamic: classifier
Dynamic: description
Dynamic: description-content-type
Dynamic: home-page
Dynamic: license-file
Dynamic: requires-dist
Dynamic: requires-python
Dynamic: summary
